{
  "response": {
    "header": {
      "resultCode": "00",
      "resultMsg": "NORMAL_SERVICE"
    },
    "body": {
      "items": {
        "item": [
          {
            "NCS_LCLAS_CD": "02",
            "NCS_LCLAS_CDNM": "경영·회계·사무",
            "NCS_MCLAS_CD": "04",
            "NCS_MCLAS_CDNM": "생산·품질관리",
            "NCS_SCLAS_CD": "03",
            "NCS_SCLAS_CDNM": "물류무역관리",
            "NCS_SUBD_CD": "03",
            "NCS_SUBD_CDNM": "원산지관리",
            "NCS_DEGR": 28,
            "USG_YN": "Y",
            "NCS_COMPE_UNIT_CD": "01",
            "DEVEL_YY": "2015",
            "VER_NO": 1,
            "NCS_CL_CD": "0204030301_15v1",
            "COMPE_UNIT_NAME": "FTA 원산지 활용분석",
            "COMPE_UNIT_DEF": "FTA 원산지 활용분석이란 FTA 활용의 필요성 및 업종별 특수성을 분석하여 효과적인 원산지관리 체계를 수립하는 능력이다.",
            "COMPE_UNIT_LEVEL": 4
          },
          {
            "NCS_LCLAS_CD": "02",
            "NCS_LCLAS_CDNM": "경영·회계·사무",
            "NCS_MCLAS_CD": "04",
            "NCS_MCLAS_CDNM": "생산·품질관리",
            "NCS_SCLAS_CD": "03",
            "NCS_SCLAS_CDNM": "물류무역관리",
            "NCS_SUBD_CD": "03",
            "NCS_SUBD_CDNM": "원산지관리",
            "NCS_DEGR": 28,
            "USG_YN": "Y",
            "NCS_COMPE_UNIT_CD": "02",
            "DEVEL_YY": "2015",
            "VER_NO": 1,
            "NCS_CL_CD": "0204030302_15v1",
            "COMPE_UNIT_NAME": "FTA 원산지 판정요소관리",
            "COMPE_UNIT_DEF": "FTA 원산지 판정요소 관리란 품목분류 및 원산지 기준을 확인하여 원산지를 관리하고 FTA BOM을 구성하는 능력이다.",
            "COMPE_UNIT_LEVEL": 4
          },
          {
            "NCS_LCLAS_CD": "02",
            "NCS_LCLAS_CDNM": "경영·회계·사무",
            "NCS_MCLAS_CD": "04",
            "NCS_MCLAS_CDNM": "생산·품질관리",
            "NCS_SCLAS_CD": "03",
            "NCS_SCLAS_CDNM": "물류무역관리",
            "NCS_SUBD_CD": "03",
            "NCS_SUBD_CDNM": "원산지관리",
            "NCS_DEGR": 28,
            "USG_YN": "Y",
            "NCS_COMPE_UNIT_CD": "03",
            "DEVEL_YY": "2015",
            "VER_NO": 1,
            "NCS_CL_CD": "0204030303_15v1",
            "COMPE_UNIT_NAME": "FTA 원산지 판정",
            "COMPE_UNIT_DEF": "FTA 원산지 판정이란 FTA 원산지 규정에 따라서 물품의 원산지 기준 충족 여부를 판단하는 능력이다.",
            "COMPE_UNIT_LEVEL": 5
          },
          {
            "NCS_LCLAS_CD": "02",
            "NCS_LCLAS_CDNM": "경영·회계·사무",
            "NCS_MCLAS_CD": "04",
            "NCS_MCLAS_CDNM": "생산·품질관리",
            "NCS_SCLAS_CD": "03",
            "NCS_SCLAS_CDNM": "물류무역관리",
            "NCS_SUBD_CD": "03",
            "NCS_SUBD_CDNM": "원산지관리",
            "NCS_DEGR": 28,
            "USG_YN": "Y",
            "NCS_COMPE_UNIT_CD": "04",
            "DEVEL_YY": "2015",
            "VER_NO": 1,
            "NCS_CL_CD": "0204030304_15v1",
            "COMPE_UNIT_NAME": "FTA 원산지 증빙서류 발급",
            "COMPE_UNIT_DEF": "FTA 원산지 증빙서류 발급이란 원산지 입증서류를 구비하여 원산지 증빙서류등을 발급 및 작성하는 능력이다.",
            "COMPE_UNIT_LEVEL": 2
          },
          {
            "NCS_LCLAS_CD": "02",
            "NCS_LCLAS_CDNM": "경영·회계·사무",
            "NCS_MCLAS_CD": "04",
            "NCS_MCLAS_CDNM": "생산·품질관리",
            "NCS_SCLAS_CD": "03",
            "NCS_SCLAS_CDNM": "물류무역관리",
            "NCS_SUBD_CD": "03",
            "NCS_SUBD_CDNM": "원산지관리",
            "NCS_DEGR": 28,
            "USG_YN": "Y",
            "NCS_COMPE_UNIT_CD": "05",
            "DEVEL_YY": "2015",
            "VER_NO": 1,
            "NCS_CL_CD": "0204030305_15v1",
            "COMPE_UNIT_NAME": "FTA 원산지 인증수출자 인증",
            "COMPE_UNIT_DEF": "FTA원산지 인증수출자 인증이란 원산지 인증수출자 제도를 파악하고 원산지 인증수출자 인증 관련 자료를 준비하여 인증을 취득하고 유지하는 능력이다.",
            "COMPE_UNIT_LEVEL": 3
          },
          {
            "NCS_LCLAS_CD": "02",
            "NCS_LCLAS_CDNM": "경영·회계·사무",
            "NCS_MCLAS_CD": "04",
            "NCS_MCLAS_CDNM": "생산·품질관리",
            "NCS_SCLAS_CD": "03",
            "NCS_SCLAS_CDNM": "물류무역관리",
            "NCS_SUBD_CD": "03",
            "NCS_SUBD_CDNM": "원산지관리",
            "NCS_DEGR": 28,
            "USG_YN": "Y",
            "NCS_COMPE_UNIT_CD": "06",
            "DEVEL_YY": "2015",
            "VER_NO": 1,
            "NCS_CL_CD": "0204030306_15v1",
            "COMPE_UNIT_NAME": "FTA 원산지 수입 활용",
            "COMPE_UNIT_DEF": "FTA 원산지 수입 활용이란 수입물품에서 FTA 혜택을 활용하기 위해 FTA 원산지 증빙서류 검토, FTA 특혜관세 신청 및 사후관리하는 능력이다.",
            "COMPE_UNIT_LEVEL": 4
          },
          {
            "NCS_LCLAS_CD": "02",
            "NCS_LCLAS_CDNM": "경영·회계·사무",
            "NCS_MCLAS_CD": "04",
            "NCS_MCLAS_CDNM": "생산·품질관리",
            "NCS_SCLAS_CD": "03",
            "NCS_SCLAS_CDNM": "물류무역관리",
            "NCS_SUBD_CD": "03",
            "NCS_SUBD_CDNM": "원산지관리",
            "NCS_DEGR": 28,
            "USG_YN": "Y",
            "NCS_COMPE_UNIT_CD": "07",
            "DEVEL_YY": "2015",
            "VER_NO": 1,
            "NCS_CL_CD": "0204030307_15v1",
            "COMPE_UNIT_NAME": "FTA 원산지 검증 대응",
            "COMPE_UNIT_DEF": "FTA 원산지 검증 대응이란 원산지 검증절차 및 사례를 분석하여 검증에 대응하는 능력이다.",
            "COMPE_UNIT_LEVEL": 5
          },
          {
            "NCS_LCLAS_CD": "02",
            "NCS_LCLAS_CDNM": "경영·회계·사무",
            "NCS_MCLAS_CD": "04",
            "NCS_MCLAS_CDNM": "생산·품질관리",
            "NCS_SCLAS_CD": "03",
            "NCS_SCLAS_CDNM": "물류무역관리",
            "NCS_SUBD_CD": "03",
            "NCS_SUBD_CDNM": "원산지관리",
            "NCS_DEGR": 28,
            "USG_YN": "Y",
            "NCS_COMPE_UNIT_CD": "08",
            "DEVEL_YY": "2015",
            "VER_NO": 1,
            "NCS_CL_CD": "0204030308_15v1",
            "COMPE_UNIT_NAME": "FTA 원산지 활용전략수립",
            "COMPE_UNIT_DEF": "FTA 원산지 활용 전략 수립이란 FTA 활용 성공사례를 분석하여 해외시장에 진출하고자 계획을 수립하는 능력이다.",
            "COMPE_UNIT_LEVEL": 6
          }
        ]
      },
      "pageNo": 1,
      "numOfRows": 200,
      "totalCount": 8,
      "lastPageNo": 1
    }
  }
}