{
  "response": {
    "header": {
      "resultCode": "00",
      "resultMsg": "NORMAL_SERVICE"
    },
    "body": {
      "items": {
        "item": [
          {
            "NCS_LCLAS_CD": "15",
            "NCS_LCLAS_CDNM": "기계",
            "NCS_MCLAS_CD": "06",
            "NCS_MCLAS_CDNM": "자동차",
            "NCS_SCLAS_CD": "03",
            "NCS_SCLAS_CDNM": "자동차정비",
            "NCS_SUBD_CD": "01",
            "NCS_SUBD_CDNM": "자동차전기·전자장치정비",
            "NCS_DEGR": 28,
            "DUTY_DEF": "자동차 전기·전자장치 정비는 자동차 전기·전자장치의 원리를 이해하고, 정비지침서에 따라 각종 진단장비를 활용하여 점검·진단·분석한 후, 수리 또는 교환하고 정상적인 작동여부를 검사하는 일이다.",
            "DUTY_ORD": 1,
            "USG_YN": "Y"
          },
          {
            "NCS_LCLAS_CD": "15",
            "NCS_LCLAS_CDNM": "기계",
            "NCS_MCLAS_CD": "06",
            "NCS_MCLAS_CDNM": "자동차",
            "NCS_SCLAS_CD": "03",
            "NCS_SCLAS_CDNM": "자동차정비",
            "NCS_SUBD_CD": "02",
            "NCS_SUBD_CDNM": "자동차엔진정비",
            "NCS_DEGR": 28,
            "DUTY_DEF": "자동차엔진정비는 자동차의 성능유지와 안전주행을 위해 엔진본체, 냉각장치, 윤활장치, 연료장치, 엔진점화장치, 흡·배기제어장치, 과급장치, 가솔린·LPG·디젤 전자제어장치, 배출가스 제어장치를 정비하고 정상 작동여부를 확인하는 일이다. ",
            "DUTY_ORD": 1,
            "USG_YN": "Y"
          },
          {
            "NCS_LCLAS_CD": "15",
            "NCS_LCLAS_CDNM": "기계",
            "NCS_MCLAS_CD": "06",
            "NCS_MCLAS_CDNM": "자동차",
            "NCS_SCLAS_CD": "03",
            "NCS_SCLAS_CDNM": "자동차정비",
            "NCS_SUBD_CD": "03",
            "NCS_SUBD_CDNM": "자동차섀시정비",
            "NCS_DEGR": 28,
            "DUTY_DEF": "자동차섀시정비는 자동차의 성능유지와 안전주행을 위해 클러치·수동변속기, 자동변속기, 드라이브라인, 유압식·전자제어 현가장치, 조향장치, 제동장치, 휠·타이어·얼라인먼트, 주행안전보조시스템을 정비하고 정상작동여부를 확인하는 일이다.",
            "DUTY_ORD": 2,
            "USG_YN": "Y"
          },
          {
            "NCS_LCLAS_CD": "15",
            "NCS_LCLAS_CDNM": "기계",
            "NCS_MCLAS_CD": "06",
            "NCS_MCLAS_CDNM": "자동차",
            "NCS_SCLAS_CD": "03",
            "NCS_SCLAS_CDNM": "자동차정비",
            "NCS_SUBD_CD": "04",
            "NCS_SUBD_CDNM": "자동차차체정비",
            "NCS_DEGR": 28,
            "DUTY_DEF": "자동차 차체정비는 변형된 자동차의 파손된 부분을 분석하고 계측하여 차체정비계획을 수립하고 변형된 차체를 수정 및 교환하여 차체정비 마무리 점검을 통하여 자동차 차체 구조강도와 안전을 유지하도록 원상복구 하는 일이다.",
            "DUTY_ORD": 4,
            "USG_YN": "Y"
          },
          {
            "NCS_LCLAS_CD": "15",
            "NCS_LCLAS_CDNM": "기계",
            "NCS_MCLAS_CD": "06",
            "NCS_MCLAS_CDNM": "자동차",
            "NCS_SCLAS_CD": "03",
            "NCS_SCLAS_CDNM": "자동차정비",
            "NCS_SUBD_CD": "05",
            "NCS_SUBD_CDNM": "자동차도장",
            "NCS_DEGR": 28,
            "DUTY_DEF": "자동차 도장이란 도료를 이용하여 차체의 부식 등 손상을 방지하고 외관을 아름답고 상품성을 향상시키기 위하여 손상된 도막을 수리 복원하고 특수목적을 부여하기 위하여 자동차에 도장하는 일이다.",
            "DUTY_ORD": 5,
            "USG_YN": "Y"
          },
          {
            "NCS_LCLAS_CD": "15",
            "NCS_LCLAS_CDNM": "기계",
            "NCS_MCLAS_CD": "06",
            "NCS_MCLAS_CDNM": "자동차",
            "NCS_SCLAS_CD": "03",
            "NCS_SCLAS_CDNM": "자동차정비",
            "NCS_SUBD_CD": "06",
            "NCS_SUBD_CDNM": "자동차정비검사",
            "NCS_DEGR": 28,
            "DUTY_DEF": "자동차 정비검사는 자동차 관련법규와 검사기준에 따라 각종 공구, 기기 및 점검장비를 이용하여 엔진, 섀시. 전기전자장치 등의 단위별 안전도와 배출가스 허용기준 적합여부 등을 진단, 검사하는 일이다.",
            "DUTY_ORD": 1,
            "USG_YN": "Y"
          },
          {
            "NCS_LCLAS_CD": "15",
            "NCS_LCLAS_CDNM": "기계",
            "NCS_MCLAS_CD": "06",
            "NCS_MCLAS_CDNM": "자동차",
            "NCS_SCLAS_CD": "03",
            "NCS_SCLAS_CDNM": "자동차정비",
            "NCS_SUBD_CD": "07",
            "NCS_SUBD_CDNM": "전기자동차정비",
            "NCS_DEGR": 28,
            "DUTY_DEF": "전기자동차정비는 차량의 성능 유지와 안전한 주행을 위하여 전기자동차 작동원리에 대한 지식과  정비 지침서에 따라 진단 장비를 활용하여 정비 및 정상 작동 여부를 검사하는 일이다. ",
            "DUTY_ORD": 1,
            "USG_YN": "Y"
          },
          {
            "NCS_LCLAS_CD": "15",
            "NCS_LCLAS_CDNM": "기계",
            "NCS_MCLAS_CD": "06",
            "NCS_MCLAS_CDNM": "자동차",
            "NCS_SCLAS_CD": "03",
            "NCS_SCLAS_CDNM": "자동차정비",
            "NCS_SUBD_CD": "08",
            "NCS_SUBD_CDNM": "전기자동차검사",
            "NCS_DEGR": 28,
            "DUTY_DEF": " 전기자동차검사는 자동차관리법과 관련 법령에 따라 고전원을 사용하는 자동차를 대상으로 운행안전성을 정기적으로 확인하는 일이다. ",
            "DUTY_ORD": 1,
            "USG_YN": "Y"
          }
        ]
      },
      "pageNo": 1,
      "numOfRows": 200,
      "totalCount": 8,
      "lastPageNo": 1
    }
  }
}